lemaitre/bandpasses/__init__.py
lemaitre/bandpasses/builtins.py
lemaitre/bandpasses/flibs.py
lemaitre/bandpasses/flycheck_builtins.py
lemaitre/bandpasses/plots.py
lemaitre/bandpasses/data/hsc_v0.hdf5
lemaitre/bandpasses/data/megacam6_v0.hdf5
lemaitre/bandpasses/data/ztf_v0.hdf5
lemaitre_bandpasses-0.2.0.dist-info/METADATA
lemaitre_bandpasses-0.2.0.dist-info/WHEEL
lemaitre_bandpasses-0.2.0.dist-info/top_level.txt
lemaitre_bandpasses-0.2.0.dist-info/RECORD
