Metadata-Version: 2.1
Name: lemaitre-bandpasses
Version: 0.2.0
Summary: A small package to store and distribute the Lemaitre bandpasses
Home-page: https://gitlab.in2p3.fr/lemaitre/bandpasses
Author: Nicolas Regnault
Author-email: nicolas.regnault@lpnhe.in2p3.fr
License: MIT
Keywords: astronomy,astrophysics
Classifier: Development Status :: 2 - Pre-Alpha
Classifier: Intended Audience :: Science/Research
Classifier: License :: OSI Approved :: Apache Software License
Classifier: Programming Language :: Python :: 3
Classifier: Topic :: Scientific/Engineering :: Astronomy
Classifier: Topic :: Scientific/Engineering :: Physics
Requires-Python: >=3.8
Requires-Dist: requests
Requires-Dist: numpy
Requires-Dist: pandas
Requires-Dist: scipy
Requires-Dist: scikit-sparse
Requires-Dist: matplotlib
Requires-Dist: sncosmo
Requires-Dist: astropy
Requires-Dist: h5py
Requires-Dist: bbf
Requires-Dist: importlib-metadata ; python_version < "3.10"
Provides-Extra: pdf
Requires-Dist: ReportLab >=1.2 ; extra == 'pdf'
Requires-Dist: RXP ; extra == 'pdf'
Provides-Extra: rest
Requires-Dist: docutils >=0.3 ; extra == 'rest'
Requires-Dist: pack ==1.1,==1.3 ; extra == 'rest'
